flake8_pytest_importorskip/__init__.py
flake8_pytest_importorskip-1.1.0.dist-info/entry_points.txt
flake8_pytest_importorskip-1.1.0.dist-info/LICENSE
flake8_pytest_importorskip-1.1.0.dist-info/WHEEL
flake8_pytest_importorskip-1.1.0.dist-info/METADATA
flake8_pytest_importorskip-1.1.0.dist-info/RECORD
