Metadata-Version: 2.1
Name: flake8-pytest-importorskip
Version: 1.1.0
Summary: Make pycodestyle treat pytest.importorskip as an import statement (avoid E402)
Home-page: https://pypi.org/project/flake8-pytest-importorskip
License: Apache 2.0
Author: Ash Berlin-Taylor
Author-email: ash@apache.org
Requires-Python: >=3.6,<4.0
Classifier: License :: Other/Proprietary License
Classifier: Programming Language :: Python :: 3
Classifier: Programming Language :: Python :: 3.6
Classifier: Programming Language :: Python :: 3.7
Classifier: Programming Language :: Python :: 3.8
Classifier: Programming Language :: Python :: 3.9
Requires-Dist: flake8 (>=3)
Requires-Dist: kgb (>=6.0,<7.0)
Requires-Dist: pycodestyle (>=2.6.0,<3.0.0)
Project-URL: Repository, https://github.com/ashb/flake8-pytest-importorskip
